lincbrain/__init__.py
lincbrain/_version.py
lincbrain/conftest.py
lincbrain/consts.py
lincbrain/dandiapi.py
lincbrain/dandiarchive.py
lincbrain/dandiset.py
lincbrain/delete.py
lincbrain/download.py
lincbrain/due.py
lincbrain/exceptions.py
lincbrain/keyring.py
lincbrain/misctypes.py
lincbrain/move.py
lincbrain/organize.py
lincbrain/pynwb_utils.py
lincbrain/upload.py
lincbrain/utils.py
lincbrain/validate.py
lincbrain/validate_types.py
lincbrain/cli/__init__.py
lincbrain/cli/base.py
lincbrain/cli/cmd_delete.py
lincbrain/cli/cmd_digest.py
lincbrain/cli/cmd_download.py
lincbrain/cli/cmd_instances.py
lincbrain/cli/cmd_ls.py
lincbrain/cli/cmd_move.py
lincbrain/cli/cmd_organize.py
lincbrain/cli/cmd_service_scripts.py
lincbrain/cli/cmd_shell_completion.py
lincbrain/cli/cmd_upload.py
lincbrain/cli/cmd_validate.py
lincbrain/cli/command.py
lincbrain/cli/formatter.py
lincbrain/cli/tests/__init__.py
lincbrain/cli/tests/test_cmd_ls.py
lincbrain/cli/tests/test_cmd_validate.py
lincbrain/cli/tests/test_command.py
lincbrain/cli/tests/test_digest.py
lincbrain/cli/tests/test_download.py
lincbrain/cli/tests/test_formatter.py
lincbrain/cli/tests/test_instances.py
lincbrain/cli/tests/test_move.py
lincbrain/cli/tests/test_service_scripts.py
lincbrain/cli/tests/test_shell_completion.py
lincbrain/cli/tests/data/update_dandiset_from_doi/biorxiv.json
lincbrain/cli/tests/data/update_dandiset_from_doi/biorxiv.vcr.yaml
lincbrain/cli/tests/data/update_dandiset_from_doi/elife.json
lincbrain/cli/tests/data/update_dandiset_from_doi/elife.vcr.yaml
lincbrain/cli/tests/data/update_dandiset_from_doi/jneurosci.json
lincbrain/cli/tests/data/update_dandiset_from_doi/jneurosci.vcr.yaml
lincbrain/cli/tests/data/update_dandiset_from_doi/nature.json
lincbrain/cli/tests/data/update_dandiset_from_doi/nature.vcr.yaml
lincbrain/cli/tests/data/update_dandiset_from_doi/neuron.json
lincbrain/cli/tests/data/update_dandiset_from_doi/neuron.vcr.yaml
lincbrain/files/__init__.py
lincbrain/files/_private.py
lincbrain_cli-0.11.4.dist-info/LICENSE
lincbrain_cli-0.11.4.dist-info/METADATA
lincbrain_cli-0.11.4.dist-info/WHEEL
lincbrain_cli-0.11.4.dist-info/entry_points.txt
lincbrain_cli-0.11.4.dist-info/top_level.txt
lincbrain_cli-0.11.4.dist-info/RECORD
