Metadata-Version: 2.1
Name: lincbrain-cli
Version: 0.11.4
Summary: Command line client for interaction with LINC Brain archive elements
Home-page: http://lincbrain.org
Author: LINC developers
Author-email: team@lincbrain.org
Maintainer: Aaron Kanzer
Maintainer-email: akanzer@mit.edu
License: Apache 2.0
Project-URL: Source Code, https://github.com/lincbrain/linc-cli
Project-URL: Documentation, https://dandi.readthedocs.io
Platform: OS Independent
Classifier: Development Status :: 1 - Planning
Classifier: Environment :: Console
Classifier: Intended Audience :: Science/Research
Classifier: License :: OSI Approved :: Apache Software License
Classifier: Operating System :: OS Independent
Classifier: Programming Language :: Python
Classifier: Programming Language :: Python :: 3.8
Classifier: Programming Language :: Python :: 3.9
Classifier: Programming Language :: Python :: 3.10
Classifier: Programming Language :: Python :: 3.11
Classifier: Programming Language :: Python :: 3.12
Classifier: Topic :: Scientific/Engineering
Requires-Python: >=3.8
License-File: LICENSE
Requires-Dist: bidsschematools~=0.7.0
Requires-Dist: click>=7.1
Requires-Dist: click-didyoumean
Requires-Dist: dandischema==0.10.4
Requires-Dist: etelemetry>=0.2.2
Requires-Dist: fasteners
Requires-Dist: fscacher>=0.3.0
Requires-Dist: hdmf!=3.5.0
Requires-Dist: humanize
Requires-Dist: interleave~=0.1
Requires-Dist: joblib
Requires-Dist: keyring!=23.9.0
Requires-Dist: keyrings.alt
Requires-Dist: packaging
Requires-Dist: platformdirs
Requires-Dist: pycryptodomex
Requires-Dist: pydantic~=2.0
Requires-Dist: pynwb!=1.1.0,!=2.3.0,>=1.0.3
Requires-Dist: nwbinspector!=0.4.32,>=0.4.28
Requires-Dist: pyout!=0.6.0,>=0.5
Requires-Dist: python-dateutil
Requires-Dist: requests~=2.20
Requires-Dist: ruamel.yaml<1,>=0.15
Requires-Dist: semantic-version
Requires-Dist: tenacity
Requires-Dist: yarl~=1.9
Requires-Dist: zarr~=2.10
Requires-Dist: zarr-checksum~=0.4.0
Provides-Extra: all
Requires-Dist: allensdk; extra == "all"
Requires-Dist: duecredit; extra == "all"
Requires-Dist: fsspec[http]; extra == "all"
Requires-Dist: flake8; extra == "all"
Requires-Dist: pre-commit; extra == "all"
Requires-Dist: anys~=0.2; extra == "all"
Requires-Dist: coverage; extra == "all"
Requires-Dist: opencv-python; extra == "all"
Requires-Dist: pytest; extra == "all"
Requires-Dist: pytest-cov; extra == "all"
Requires-Dist: pytest-mock; extra == "all"
Requires-Dist: pytest-rerunfailures; extra == "all"
Requires-Dist: pytest-timeout; extra == "all"
Requires-Dist: responses!=0.24.0; extra == "all"
Requires-Dist: vcrpy; extra == "all"
Requires-Dist: boto3; extra == "all"
Provides-Extra: extensions
Requires-Dist: allensdk; extra == "extensions"
Provides-Extra: extras
Requires-Dist: duecredit; extra == "extras"
Requires-Dist: fsspec[http]; extra == "extras"
Provides-Extra: style
Requires-Dist: flake8; extra == "style"
Requires-Dist: pre-commit; extra == "style"
Provides-Extra: test
Requires-Dist: anys~=0.2; extra == "test"
Requires-Dist: coverage; extra == "test"
Requires-Dist: opencv-python; extra == "test"
Requires-Dist: pytest; extra == "test"
Requires-Dist: pytest-cov; extra == "test"
Requires-Dist: pytest-mock; extra == "test"
Requires-Dist: pytest-rerunfailures; extra == "test"
Requires-Dist: pytest-timeout; extra == "test"
Requires-Dist: responses!=0.24.0; extra == "test"
Requires-Dist: vcrpy; extra == "test"
Provides-Extra: tools
Requires-Dist: boto3; extra == "tools"
